{
  "project_info": {
    "project_number": "654386197077",
    "firebase_url": "https://ewg-healthyliving.firebaseio.com",
    "project_id": "ewg-healthyliving",
    "storage_bucket": "ewg-healthyliving.firebasestorage.app"
  },
  "client": [
    {
      "client_info": {
        "mobilesdk_app_id": "1:654386197077:android:513a75e85697455a9a5adc",
        "android_client_info": {
          "package_name": "com.skindeep.mobile"
        }
      },
      "oauth_client": [
        {
          "client_id": "654386197077-5m80286mn31ihi3ja537341l2hmbfv66.apps.googleusercontent.com",
          "client_type": 1,
          "android_info": {
            "package_name": "com.skindeep.mobile",
            "certificate_hash": "34debf6ef1a0f4419d5a1e25e60707756302a492"
          }
        },
        {
          "client_id": "654386197077-98jq252n34mtq83ll6bekq8d5vkohkcc.apps.googleusercontent.com",
          "client_type": 1,
          "android_info": {
            "package_name": "com.skindeep.mobile",
            "certificate_hash": "7236f5c56a58674ef8725850a66440d3e1932a78"
          }
        },
        {
          "client_id": "654386197077-vtlcddbhbqnei400o6mklofppjqmgnk6.apps.googleusercontent.com",
          "client_type": 1,
          "android_info": {
            "package_name": "com.skindeep.mobile",
            "certificate_hash": "5974b847f49b0302c8314d3feb2716f722b2117a"
          }
        },
        {
          "client_id": "654386197077-kagj4boq08hnoo13j7l9ba6tbndgvq4s.apps.googleusercontent.com",
          "client_type": 3
        }
      ],
      "api_key": [
        {
          "current_key": "AIzaSyD2e-hc11M88B1czmcuqy6J4xKe7xti_Vg"
        }
      ],
      "services": {
        "appinvite_service": {
          "other_platform_oauth_client": [
            {
              "client_id": "654386197077-d5l0aq8mv334tjcigh6dd3l98o3lpt0k.apps.googleusercontent.com",
              "client_type": 3
            },
            {
              "client_id": "654386197077-q07scaq41i4pb052fee423f7tkduelpj.apps.googleusercontent.com",
              "client_type": 2,
              "ios_info": {
                "bundle_id": "skindeepR",
                "app_store_id": "703155791"
              }
            }
          ]
        }
      }
    }
  ],
  "configuration_version": "1"
}